flask_taskq/__init__.py
flask_taskq/cli.py
flask_taskq/const.py
flask_taskq/globals.py
flask_taskq/models.py
flask_taskq/py.typed
flask_taskq/queue.py
flask_taskq/task.py
flask_taskq/types.py
flask_taskq/worker.py
flask_taskq-0.1.3.dist-info/LICENSE
flask_taskq-0.1.3.dist-info/METADATA
flask_taskq-0.1.3.dist-info/WHEEL
flask_taskq-0.1.3.dist-info/RECORD
