Metadata-Version: 2.1
Name: flask-taskq
Version: 0.1.3
Summary: Database driven task queue for Flask applications
Home-page: https://github.com/TitaniumHocker/Flask-TaskQ
License: MIT
Keywords: flask,extension,task-schedules,queue
Author: Ivan Fedorov
Author-email: inbox@titaniumhocker.ru
Requires-Python: >=3.9,<4.0
Classifier: Development Status :: 3 - Alpha
Classifier: Environment :: Web Environment
Classifier: Framework :: Flask
Classifier: Intended Audience :: Developers
Classifier: License :: OSI Approved :: MIT License
Classifier: Operating System :: OS Independent
Classifier: Programming Language :: Python :: 3
Classifier: Programming Language :: Python :: 3.9
Classifier: Programming Language :: Python :: 3.10
Classifier: Programming Language :: Python :: 3.11
Classifier: Programming Language :: Python :: 3.12
Classifier: Programming Language :: Python :: 3 :: Only
Classifier: Topic :: Software Development :: Libraries
Requires-Dist: flask (>=2.0.1,<3.0)
Requires-Dist: flask-sqlalchemy (>=2.5.1)
Requires-Dist: prettytable (>=3.6.0,<4.0)
Requires-Dist: sqlalchemy-utils (>=0.38.2)
Project-URL: Bug Tracker, https://github.com/TitaniumHocker/Flask-TaskQ/issues
Project-URL: Documentation, https://flask-taskq.rtfd.io
Project-URL: Repository, https://github.com/TitaniumHocker/Flask-TaskQ
